
<item>  <title>Adão Negro</title>
<link>plugin://plugin.video.elementum/play?uri=magnet:?xt=urn:btih:8483ba53d4ecf509442073b493f7168e9f2f1a7a</link>
<thumbnail>https://www.themoviedb.org/t/p/w600_and_h900_bestv2/gE1KNghdInNh0VDcfFQlAy4PTEL.jpg</thumbnail>  <fanart>https://www.themoviedb.org/t/p/original/bQXAqRx2Fgc46uCVWgoPz5L5Dtr.jpg</fanart>
<genre>Ação, Ficção</genre> / <year>2022</year> / <rate>7.3</rate> / <aired>2022/10/20</aired> / <duration>7500</duration>
<info>"[I]O mundo precisava de um herói. Agora ele tem Adão Negro.[/I]"

Quase 5.000 anos depois de ter sido concedido com os poderes onipotentes dos deuses egípcios - e de ter sido preso, - Adão Negro se ergue de seu túmulo, pronto para trazer sua justiça ao mundo moderno.</info> </item>
----------------------------------------
<item>  <title>Pantera Negra: Wakanda para Sempre</title>  <link>plugin://plugin.video.elementum/play?uri=magnet:?xt=urn:btih:ad968bea28342f0b8f5d2e84b26c20cf6d4951d8</link>
<thumbnail>https://www.themoviedb.org/t/p/w600_and_h900_bestv2/6tb0qiqLN9szHPA4i0kY38oaWew.jpg</thumbnail>  <fanart>https://www.themoviedb.org/t/p/original/yYrvN5WFeGYjJnRzhY0QXuo4Isw.jpg</fanart>
<genre>Ação, Aventura, Ficção científica</genre> / <year>2022</year> / <rate></rate> / <aired>2022/11/10</aired> / <duration>9120</duration>
<info>"[I]Para Sempre[/I]"

Rainha Ramonda, Shuri, M'Baku, Okoye e Dora Milaje, lutam para proteger sua nação das potências mundiais intervenientes após a morte do rei T'Challa. Enquanto os wakandanos se esforçam para abraçar seu próximo capítulo, os heróis devem se unir com a ajuda de War Dog Nakia e Everett Ross e forjar um novo caminho para o reino de Wakanda.</info> </item>
--------------------------------------------
--------------------------------
<item>  <title>Amsterdam</title>  <link>plugin://plugin.video.elementum/play?uri=magnet:?xt=urn:btih:8860f1140077341e3c6704f7c3f7c26c79f3d571</link>
<thumbnail>https://www.themoviedb.org/t/p/w600_and_h900_bestv2/chCrPG0LJeilfJwsWPAfmWiJI2T.jpg</thumbnail>  <fanart></fanart>
<genre>Comédia, Mistério, Thriller, Crime, Drama</genre> / <year>2022</year> / <rate>6.2</rate> / <aired>2022/11/03</aired> / <duration>7920</duration>
<info>Três amigos - um médico, uma enfermeira e um advogado - tornam-se os principais suspeitos de um assassinato na década de 1930.</info> </item>
----------------------------------------------------------------------------

<item>  <title>Adão Negro</title>
<link>plugin://plugin.video.elementum/play?uri=magnet:?xt=urn:btih:ab81855ad4cc11582a808533515ee054bb3c2c86$nome=Adao Negro 2022 - Dub</link>
<link>plugin://plugin.video.elementum/play?uri=magnet:?xt=urn:btih:e05fd141d2327f1bb08203d30471e62773bbdedc$nome=Black Adam 2022 - Leg</link>
<thumbnail>https://www.themoviedb.org/t/p/w600_and_h900_bestv2/gE1KNghdInNh0VDcfFQlAy4PTEL.jpg</thumbnail>  <fanart>https://www.themoviedb.org/t/p/original/bQXAqRx2Fgc46uCVWgoPz5L5Dtr.jpg</fanart>
<genre>Ação, Ficção</genre> / <year>2022</year> / <rate>7.3</rate> / <aired>2022/10/20</aired> / <duration>7500</duration>
<info>"[I]O mundo precisava de um herói. Agora ele tem Adão Negro.[/I]"

Quase 5.000 anos depois de ter sido concedido com os poderes onipotentes dos deuses egípcios - e de ter sido preso, - Adão Negro se ergue de seu túmulo, pronto para trazer sua justiça ao mundo moderno.</info> </item>
----------------------------------------------------------------------------

<item> 
<title>Sorria</title>
<link>plugin://plugin.video.elementum/play?uri=magnet:?xt=urn:btih:f682382b6cdb7e3faf1e93df509dece618c41ab7</link>
<thumbnail>https://www.themoviedb.org/t/p/w600_and_h900_bestv2/gJbMkl9e2NZcjlKpXuK9QaExobN.jpg</thumbnail>
<fanart>https://www.themoviedb.org/t/p/original/mVNPfpydornVe4H4UCIk7WevWjf.jpg</fanart>
<genre>Terror, Mistério, Thriller</genre>
<year>2022</year>
<rate>7.0</rate>
<aired>2022/09/23</aired>
<duration>6900</duration>
<info>"[I]Uma vez que você vê. É tarde demais[/I]"

Após testemunhar um acidente traumático e bizarro envolvendo um paciente, a Dra. Rose Cotter começa a vivenciar eventos assustadores que ela não consegue explicar.</info>
</item>
----------------------------------------------------------------------------

<item> 
<title>A Mulher Rei</title>
<link>plugin://plugin.video.elementum/play?uri=magnet:?xt=urn:btih:6a45b8617cea58627a474a1fd92c568815391fa5</link>
<thumbnail>https://www.themoviedb.org/t/p/original/ml7Ypdeev7s1MK38dQN0OXoZ8p9.jpg</thumbnail>
<fanart>https://www.themoviedb.org/t/p/original/mSuXg6tn3kqUjBiTlSBcL5XOwen.jpg</fanart>
<genre>Ação, Drama, História</genre>
<year>2022</year>
<rate>6.1</rate>
<aired>2022/09/15</aired>
<duration>8100</duration>
<info>"[I]Seu reinado começa.[/I]"

Nanisca era a comandante do exército do Reino de Daomé, um dos locais mais poderosos da África nos séculos XVII e XIX. Durante o período, o grupo militar era composto apenas por mulheres, entre as guerreiras está a filha de Nanisca, Nawi, juntas elas combateram os colonizadores franceses, tribos rivais e todos aqueles que tentaram escravizar seu povo e destruir suas terras.</info>
</item>
----------------------------------------------------------------------------
